{
  "updated_at": "2026-06-05T14:13:09.301426+00:00",
  "prices": {
    "SPY": {
      "price": 749.67,
      "change": -7.42,
      "changePct": -0.9801,
      "high": 752.82,
      "low": 748.225,
      "prevClose": 757.09
    },
    "QQQ": {
      "price": 725.19,
      "change": -15.42,
      "changePct": -2.0821,
      "high": 731.69,
      "low": 723.34,
      "prevClose": 740.61
    },
    "NVDA": {
      "price": 212.12,
      "change": -6.54,
      "changePct": -2.9909,
      "high": 214.95499999999998,
      "low": 211.54,
      "prevClose": 218.66
    },
    "PLTR": {
      "price": 138.35,
      "change": -3.35,
      "changePct": -2.3641,
      "high": 141.97,
      "low": 137.7,
      "prevClose": 141.7
    },
    "TSLA": {
      "price": 409.1,
      "change": -9.35,
      "changePct": -2.2344,
      "high": 424.6799,
      "low": 408.75,
      "prevClose": 418.45
    },
    "AAPL": {
      "price": 312.89,
      "change": 1.66,
      "changePct": 0.5334,
      "high": 314.5,
      "low": 311.83000000000004,
      "prevClose": 311.23
    },
    "AMD": {
      "price": 489.73,
      "change": -33.47,
      "changePct": -6.3972,
      "high": 505.62,
      "low": 484.26,
      "prevClose": 523.2
    },
    "IWM": {
      "price": 286.83,
      "change": -5.18,
      "changePct": -1.7739,
      "high": 289.595,
      "low": 285.63,
      "prevClose": 292.01
    },
    "GLD": {
      "price": 401.18,
      "change": -10.09,
      "changePct": -2.4534,
      "high": 406.935,
      "low": 400.54,
      "prevClose": 411.27
    }
  }
}