{
  "updated_at": "2026-06-02T17:16:58.095601Z",
  "vix": 15.92,
  "treasury_10y": 4.45,
  "prices": {
    "SPY": {
      "price": 759.72,
      "changePct": 0.16,
      "high": 760.4,
      "low": 756.75
    },
    "QQQ": {
      "price": 745.53,
      "changePct": 0.38,
      "high": 746.23,
      "low": 739.23
    },
    "NVDA": {
      "price": 225.05,
      "changePct": 0.31,
      "high": 232.28,
      "low": 224.15
    },
    "PLTR": {
      "price": 153.08,
      "changePct": -4.71,
      "high": 159.55,
      "low": 149.8
    },
    "TSLA": {
      "price": 423,
      "changePct": 1.71,
      "high": 423.47,
      "low": 413.65
    },
    "AAPL": {
      "price": 314.95,
      "changePct": 2.82,
      "high": 315.1,
      "low": 306.69
    },
    "AMD": {
      "price": 513.96,
      "changePct": 0.75,
      "high": 519.95,
      "low": 501.22
    },
    "IWM": {
      "price": 290.72,
      "changePct": 0.6,
      "high": 291.87,
      "low": 288.4
    },
    "GLD": {
      "price": 412.1,
      "changePct": 0.2,
      "high": 415.25,
      "low": 411.79
    }
  }
}